agent_vrm_mcp/README.md
agent_vrm_mcp/__init__.py
agent_vrm_mcp/__main__.py
agent_vrm_mcp/server.py
agent_vrm_mcp-0.1.0.dist-info/METADATA
agent_vrm_mcp-0.1.0.dist-info/WHEEL
agent_vrm_mcp-0.1.0.dist-info/entry_points.txt
agent_vrm_mcp-0.1.0.dist-info/RECORD
