Metadata-Version: 2.4
Name: agent-vrm-mcp
Version: 0.1.0
Summary: A Model Context Protocol server providing VRM avatar functionality for LLMs
Project-URL: Repository, https://github.com/Sunwood-ai-labs/agent-vrm-mcp
Project-URL: PyPI, https://pypi.org/project/agent-vrm-mcp/
Author-email: VRM MCP Developer <example@example.com>
License: MIT
Keywords: 3d,avatar,llm,mcp,vrm
Classifier: Development Status :: 4 - Beta
Classifier: Intended Audience :: Developers
Classifier: License :: OSI Approved :: MIT License
Classifier: Programming Language :: Python :: 3
Classifier: Programming Language :: Python :: 3.10
Requires-Python: >=3.10
Requires-Dist: loguru>=0.7.0
Requires-Dist: mcp>=1.0.0
Requires-Dist: pydantic>=2.0.0
Requires-Dist: requests>=2.31.0
